README.rst
setup.py
BioCircos/BioCircos.py
BioCircos/__init__.py
BioCircos/example_advanced_plot.py
BioCircos/example_mutil_ciros_chrs.py
BioCircos/example_screw_plot.py
BioCircos/example_significate_chrs_plot.py
BioCircos/example_simple_test_show.py
BioCircos.egg-info/PKG-INFO
BioCircos.egg-info/SOURCES.txt
BioCircos.egg-info/dependency_links.txt
BioCircos.egg-info/requires.txt
BioCircos.egg-info/top_level.txt